indexing/__init__.py
indexing/main.py
google_url_bulk_indexing-1.0.7.dist-info/METADATA
google_url_bulk_indexing-1.0.7.dist-info/WHEEL
google_url_bulk_indexing-1.0.7.dist-info/entry_points.txt
google_url_bulk_indexing-1.0.7.dist-info/top_level.txt
google_url_bulk_indexing-1.0.7.dist-info/RECORD
