Metadata-Version: 2.1
Name: google-url-bulk-indexing
Version: 1.0.7
Summary: A package to submit Bulk URLs for Google Indexing using an Excel file
Author: Around With Us
Author-email: mscrabe@gmail.com
Keywords: Website URL Indexing,URL indexing,bulk indexing,Google indexing,Python package,Unlimited Indexing,SEO Tool
Classifier: Development Status :: 5 - Production/Stable
Classifier: Topic :: Software Development :: Libraries :: Python Modules
Classifier: Programming Language :: Python :: 3
Classifier: License :: OSI Approved :: MIT License
Classifier: Operating System :: OS Independent
Requires-Python: >=3.6
Requires-Dist: google-auth
Requires-Dist: google-auth-oauthlib
Requires-Dist: requests
Requires-Dist: pandas
Requires-Dist: openpyxl
